{
  "businessKey": "<businessKey>",
  "processDate": null,
  "dataSource": "INBOUND",
  "version": 1,
  "edifactVersion": 202404,
  "data": {
    "stammdaten": {
      "MARKTLOKATION": [
        {
          "boTyp": "MARKTLOKATION",
          "versionStruktur": "1",
          "marktlokationsId": "50074561228",
          "sparte": "STROM"
        }
      ],
      "ANFRAGE": [
        {
          "boTyp": "ANFRAGE",
          "versionStruktur": "1",
          "lokationsId": "50074561228",
          "lokationsTyp": "MALO",
          "anfragekategorie": "ENTSPERRUNG",
          "anfragetyp": "INNERHALB_DER_ARBEITSZEIT"
        }
      ],
      "AUFTRAG": [
        {
          "boTyp": "AUFTRAG",
          "versionStruktur": "1",
          "positionsdaten": [
            {
              "positionsnummer": 1,
              "allgemeineInformationen": {
                "info1": "Test123456"
              }
            }
          ]
        }
      ],
      "SPERRAUFTRAG": [
        {
          "boTyp": "SPERRAUFTRAG",
          "versionStruktur": "1",
          "treffpunkt": {
            "postleitzahl": "12345",
            "ort": "Musterstadt",
            "strasse": "Musterstr.",
            "hausnummer": "10",
            "landescode": "DE",
            "zusatzInformation": {
              "zusatz1": "Mustermann",
              "zusatz2": "Max"
            }
          }
        }
      ]
    },
    "transaktionsdaten": {
      "datenaustauschreferenz": "YASMINJA432380",
      "sparte": "STROM",
      "pruefidentifikator": "17117",
      "absender": {
        "boTyp": "MARKTTEILNEHMER",
        "versionStruktur": "1",
        "rollencodenummer": "9903790000002",
        "rollencodetyp": "BDEW",
        "ansprechpartner": {
          "boTyp": "ANSPRECHPARTNER",
          "versionStruktur": "1",
          "nachname": "Mustermann",
          "eMailAdresse": "mustermann@mail.de"
        }
      },
      "empfaenger": {
        "boTyp": "MARKTTEILNEHMER",
        "versionStruktur": "1",
        "rollencodenummer": "9900321000005",
        "rollencodetyp": "BDEW"
      },
      "dokumentennummer": "YASMINJA590495BGM",
      "kategorie": "Z52",
      "nachrichtendatum": "2024-04-01T08:15:00Z",
      "nachrichtenreferenznummer": "YASMINJA590495",
      "freitext": {
        "freitext1": "Test123456"
      }
    },
    "zusatzdaten": {}
  }
}