{
  "businessKey": "<businessKey>",
  "processDate": null,
  "dataSource": "INBOUND",
  "version": 1,
  "edifactVersion": 202404,
  "data": {
    "stammdaten": {
      "MARKTLOKATION": [
        {
          "boTyp": "MARKTLOKATION",
          "versionStruktur": "1",
          "marktlokationsId": "50074561188",
          "sparte": "STROM",
          "energierichtung": "EINSP",
          "bilanzierungsgebiet": "11YR00000002596Z",
          "regelzone": "10YDE-RWENET---I",
          "energieherkunft": [
            {
              "erzeugungsart": "EEG_DV"
            }
          ]
        }
      ],
      "NETZNUTZUNGSVERTRAG": [
        {
          "boTyp": "VERTRAG",
          "versionStruktur": "1",
          "vertragsart": "NETZNUTZUNGSVERTRAG",
          "sparte": "STROM",
          "vertragsbeginn": "2024-06-30T22:00:00Z",
          "lokationsId": "50074561188",
          "lokationsTyp": "MALO"
        }
      ],
      "BILANZIERUNG": [
        {
          "boTyp": "BILANZIERUNG",
          "versionStruktur": "1",
          "marktlokationsId": "50074561188"
        }
      ]
    },
    "transaktionsdaten": {
      "datenaustauschreferenz": "175938",
      "sparte": "STROM",
      "transaktionsgrund": "ZF7",
      "vorgangsnummer": "1203772272",
      "pruefidentifikator": "55154",
      "absender": {
        "boTyp": "MARKTTEILNEHMER",
        "versionStruktur": "1",
        "rollencodenummer": "9900321000005",
        "rollencodetyp": "BDEW"
      },
      "empfaenger": {
        "boTyp": "MARKTTEILNEHMER",
        "versionStruktur": "1",
        "rollencodenummer": "9903790000002",
        "rollencodetyp": "BDEW"
      },
      "dokumentennummer": "297523BGM",
      "kategorie": "E03",
      "nachrichtendatum": "2024-04-03T08:15:00Z",
      "nachrichtenreferenznummer": "297523",
      "anfragereferenznummer": "ABC123456",
      "gueltigAb": "2024-06-30T22:00:00Z",
      "antwortstatus": "ZG2",
      "antwortstatusCodeliste": "S_0023"
    },
    "zusatzdaten": {}
  }
}