[
  {
    "businessKey": "<businessKey>",
    "processDate": null,
    "dataSource": "OUTBOUND",
    "version": 1,
    "edifactVersion": 202210,
    "data": {
      "stammdaten": {
        "MESSLOKATION": [
          {
            "boTyp": "MESSLOKATION",
            "versionStruktur": "1",
            "messlokationsId": "DE0073395252733953513649640711234",
            "sparte": "STROM"
          }
        ],
        "ANFRAGE": [
          {
            "boTyp": "ANFRAGE",
            "versionStruktur": "1",
            "lokationsId": "DE0073395252733953513649640711234",
            "lokationsTyp": "MELO",
            "anfragereferenz": "REF123456",
            "anfragetyp": "NUTZUNGSUEBERLASSUNG"
          }
        ],
        "ANGEBOT": [
          {
            "boTyp": "ANGEBOT",
            "versionStruktur": "1",
            "anfragereferenz": "REF123456",
            "angebotsdatum": "2023-03-31T22:00:00Z",
            "sparte": "STROM",
            "varianten": [
              {
                "gesamtmenge": {
                  "wert": 1,
                  "einheit": "ANZAHL"
                },
                "gesamtkosten": {
                  "wert": 1000.00,
                  "waehrung": "EUR"
                },
                "teile": [
                  {
                    "positionen": [
                      {
                        "positionsbezeichung": "1",
                        "positionspreis": {
                          "wert": 150.000001
                        },
                        "positionsbetrag": {
                          "wert": 1000.00
                        },
                        "bdewArtikelnummer": "ZAEHLEINRICHTUNG"
                      }
                    ],
                    "verweisKatalognummer": {
                      "katalognummer": "1",
                      "zeilennummer": "2",
                      "versionsnummer": "3"
                    }
                  }
                ]
              }
            ]
          }
        ],
        "ZAEHLER": [
          {
            "boTyp": "ZAEHLER",
            "versionStruktur": "1",
            "zaehlernummer": "S12345678910",
            "sparte": "STROM",
            "zaehlerauspraegung": "EINRICHTUNGSZAEHLER",
            "zaehlertyp": "ELEKTRONISCHERHAUSHALTSZAEHLER",
            "tarifart": "EINTARIF",
            "herstellungsdatum": "2015",
            "eichungBis": "2025",
            "messwerterfassung": "MANUELL_AUSGELESENE",
            "zaehlertypspezifikation": "EDL40",
            "befestigungsart": "DREIPUNKT",
            "serialnummer": "12345678910",
            "herstellungsdatum": "2015"
          }
        ]
      },
      "transaktionsdaten": {
        "datenaustauschreferenz": "LF4CXU80",
        "sparte": "STROM",
        "pruefidentifikator": "15001",
        "absender": {
          "boTyp": "MARKTTEILNEHMER",
          "versionStruktur": "1",
          "rollencodenummer": "9904446000007",
          "rollencodetyp": "BDEW",
          "ansprechpartner": {
            "boTyp": "ANSPRECHPARTNER",
            "versionStruktur": "1",
            "nachname": "Max Mustermann",
            "eMailAdresse": "max@mustermann.de",
            "rufnummern": [
              {
                "nummerntyp": "FAX_DURCHWAHL",
                "rufnummer": "012345678910"
              },
              {
                "nummerntyp": "RUF_DURCHWAHL",
                "rufnummer": "012345678910"
              },
              {
                "nummerntyp": "RUF_ZENTRALE",
                "rufnummer": "012345678910"
              },
              {
                "nummerntyp": "MOBIL_NUMMER",
                "rufnummer": "012345678910"
              }
            ]
          }
        },
        "empfaenger": {
          "boTyp": "MARKTTEILNEHMER",
          "versionStruktur": "1",
          "rollencodenummer": "9905058000005",
          "rollencodetyp": "BDEW"
        },
        "dokumentennummer": "BGMLF8O9UTZ",
        "kategorie": "310",
        "nachrichtendatum": "2023-03-09T12:31:00Z",
        "nachrichtenreferenznummer": "UNHLFO99VSZ",
        "freitext": {
          "freitext1": "Text1",
          "freitext2": "Text2",
          "freitext3": "Text3",
          "freitext4": "Text4",
          "freitext5": "Text5"
        }
      },
      "zusatzdaten": {}
    }
  }
]
