[
  {
    "businessKey": "<businessKey>",
    "processDate": "<prozessDatum>",
    "dataSource": "OUTBOUND",
    "version": 1,
    "edifactVersion": 202210,
    "data": {
      "stammdaten": {
        "STATUSMITTEILUNG": [
          {
            "boTyp": "STATUSMITTEILUNG",
            "versionStruktur": "1",
            "positionsdaten": [
              {
                "positionsnummer": 1,
                "bearbeitungsdatum": "2023-01-31T23:00:00Z",
                "verwendungAb": "2023-01-30T23:00:00Z",
                "verwendungBis": "2023-02-06T23:00:00Z",
                "auftragsstatus": "GESTOERT",
                "statusanlass": "STOERUNGSBEHEBUNG_NICHT_MOEGLICH",
                "fehlerbeschreibung": {
                  "beschreibung1": "Fehlerbeschreibung"
                },
                "lokationsId": "DE0073395252733953513649640711234"
              }
            ]
          }
        ]
      },
      "transaktionsdaten": {
        "datenaustauschreferenz": "608383",
        "sparte": "STROM",
        "vorgangsnummer": "012345678910",
        "pruefidentifikator": "23009",
        "absender": {
          "boTyp": "MARKTTEILNEHMER",
          "versionStruktur": "1",
          "rollencodenummer": "9910046000008",
          "rollencodetyp": "BDEW"
        },
        "empfaenger": {
          "boTyp": "MARKTTEILNEHMER",
          "versionStruktur": "1",
          "rollencodenummer": "9900051000002",
          "rollencodetyp": "BDEW"
        },
        "dokumentennummer": "033363BGM",
        "kategorie": "4",
        "nachrichtendatum": "2023-02-17T10:07:00Z",
        "nachrichtenreferenznummer": "033363",
        "anfragereferenznummer": "012345678910"
      }
    }
  }
]
